simplepbi/__init__.py
simplepbi/admin/__init__.py
simplepbi/apps/__init__.py
simplepbi/azpause/__init__.py
simplepbi/capacities/__init__.py
simplepbi/dashboards/__init__.py
simplepbi/dataflows/__init__.py
simplepbi/datasets/__init__.py
simplepbi/fabric/__init__.py
simplepbi/fabric/adminfab/__init__.py
simplepbi/fabric/core/__init__.py
simplepbi/fabric/datapipelines/__init__.py
simplepbi/fabric/report/__init__.py
simplepbi/fabric/semanticmodels/__init__.py
simplepbi/gateways/__init__.py
simplepbi/groups/__init__.py
simplepbi/imports/__init__.py
simplepbi/pipelines/__init__.py
simplepbi/pushdatasets/__init__.py
simplepbi/reports/__init__.py
simplepbi/scorecards/__init__.py
simplepbi/token/__init__.py
simplepbi/utils/__init__.py
simplepbi-1.0.9.dist-info/licenses/LICENSE
simplepbi-1.0.9.dist-info/METADATA
simplepbi-1.0.9.dist-info/WHEEL
simplepbi-1.0.9.dist-info/top_level.txt
simplepbi-1.0.9.dist-info/RECORD
