Metadata-Version: 2.4
Name: simplepbi
Version: 1.0.9
Summary: Simplify usage of Power Bi Rest API
Home-page: 
Download-URL: 
Author: Ignacio Barrau <igna_barrau@hotmail.com>, Martin Zurita <martinzurita1@gmail.com>
Author-email: Ignacio Barrau <igna_barrau@hotmail.com>
License-Expression: MIT
Project-URL: Documentation, https://docs.microsoft.com/en-us/rest/api/power-bi/
Project-URL: SayThanks, https://www.ladataweb.com.ar/contacto.html
Project-URL: Source, https://github.com/ladataweb/SimplePBI
Project-URL: Tracker, https://github.com/ladataweb/SimplePBI/issues
Keywords: Power BI Rest API,Power BI,Power Bi API,PBI,LaDataWeb,Azure,Data,Python,Fabric,Microsoft Fabric,Fabric Rest API,Fabric API,Power BI Ops,Fabric CICD
Classifier: Development Status :: 4 - Beta
Classifier: Intended Audience :: Developers
Classifier: Programming Language :: Python :: 3
Classifier: Programming Language :: Python :: 3.7
Classifier: Programming Language :: Python :: 3.8
Classifier: Programming Language :: Python :: 3.9
Classifier: Programming Language :: Python :: 3.10
Classifier: Programming Language :: Python :: 3.11
Classifier: Operating System :: OS Independent
License-File: LICENSE
Requires-Dist: requests
Requires-Dist: pandas
Requires-Dist: msal
Requires-Dist: requests-toolbelt
Dynamic: author
Dynamic: license-file
